{
  "id": "37857791",
  "title": "Biochemical and structural basis of mercuric reductase, GbsMerA, from Gelidibacter salicanalis PAMC21136.",
  "doi": null,
  "authors": "Pardhe BD, Lee MJ, Lee JH, Do H, Oh TJ",
  "journal": "Scientific reports",
  "year": "2023",
  "abstract": "Heavy metals, including mercury, are non-biodegradable and highly toxic to microorganisms even at low concentrations. Understanding the mechanisms underlying the environmental adaptability of microorganisms with Hg resistance holds promise for their use in Hg bioremediation. We characterized GbsMerA, a mercury reductase belonging to the mercury-resistant operon of Gelidibacter salicanalis PAMC21136, and found its maximum activity of 474.7ʵmol/min/mg in reducing Hg",
  "source": "PubMed",
  "pmcid": "PMC10587081"
}